app/__init__.py
app/main.py
app/util.py
app/services/__init__.py
app/services/auth.py
app/services/base.py
app/services/brand.py
app/services/config.py
app/services/device.py
app/services/device_category.py
app/services/role.py
app/services/todo.py
app/services/user.py
cela-0.0.6a0.dist-info/METADATA
cela-0.0.6a0.dist-info/WHEEL
cela-0.0.6a0.dist-info/entry_points.txt
cela-0.0.6a0.dist-info/top_level.txt
cela-0.0.6a0.dist-info/RECORD
